LICENSE.txt
MANIFEST.in
README.rst
bootstrap.py
buildout.cfg
setup.py
docs/Makefile
docs/buildout.rst
docs/conf.py
docs/index.rst
docs/overview.rst
etc/veliberator-sample.cfg
veliberator/__init__.py
veliberator/__init__.pyc
veliberator/cartography.py
veliberator/geofinder.py
veliberator/grabber.py
veliberator/models.py
veliberator/settings.py
veliberator/station.py
veliberator/status.py
veliberator/xml_wrappers.py
veliberator.egg-info/PKG-INFO
veliberator.egg-info/SOURCES.txt
veliberator.egg-info/dependency_links.txt
veliberator.egg-info/entry_points.txt
veliberator.egg-info/not-zip-safe
veliberator.egg-info/requires.txt
veliberator.egg-info/top_level.txt
veliberator/locale/veliberator.pot
veliberator/locale/fr/LC_MESSAGES/veliberator.mo
veliberator/locale/fr/LC_MESSAGES/veliberator.po
veliberator/scripts/__init__.py
veliberator/scripts/command_line.py
veliberator/tests/__init__.py
veliberator/tests/test_cartography.py
veliberator/tests/test_geofinder.py
veliberator/tests/test_grabber.py
veliberator/tests/test_models.py
veliberator/tests/test_station.py
veliberator/tests/test_status.py
veliberator/tests/test_xml_wrappers.py
veliberator/tests/data/carto.xml
veliberator/tests/data/carto_short.xml