Metadata-Version: 1.1
Name: veliberator
Version: 0.3.3
Summary: Veliberator provides a Python API for getting informations about the stations of the Velib' network.
Home-page: https://github.com/Fantomas42/veliberator
Author: Fantomas42
Author-email: fantomas42@gmail.com
License: BSD License
Keywords: velib,api,service
Platform: any
Classifier: Intended Audience :: Developers
Classifier: Operating System :: OS Independent
Classifier: Programming Language :: Python
Classifier: License :: OSI Approved :: BSD License
Classifier: Topic :: Software Development :: Libraries :: Python Modules
